.bumpversion.cfg
.cookiecutterrc
.coveragerc
.editorconfig
.travis.yml
AUTHORS.rst
CHANGELOG.rst
CONTRIBUTING.rst
LICENSE
MANIFEST.in
README.rst
setup.cfg
setup.py
tox.ini
ci/bootstrap.py
ci/templates/.travis.yml
docs/authors.rst
docs/changelog.rst
docs/conf.py
docs/contributing.rst
docs/index.rst
docs/installation.rst
docs/readme.rst
docs/requirements.txt
docs/spelling_wordlist.txt
docs/usage.rst
docs/reference/index.rst
docs/reference/mutation_waterfall.rst
src/mutation_waterfall/__init__.py
src/mutation_waterfall/__main__.py
src/mutation_waterfall/cli.py
src/mutation_waterfall/plot.py
src/mutation_waterfall/preprocess.py
src/mutation_waterfall.egg-info/PKG-INFO
src/mutation_waterfall.egg-info/SOURCES.txt
src/mutation_waterfall.egg-info/dependency_links.txt
src/mutation_waterfall.egg-info/entry_points.txt
src/mutation_waterfall.egg-info/not-zip-safe
src/mutation_waterfall.egg-info/requires.txt
src/mutation_waterfall.egg-info/top_level.txt
tests/test.txt
tests/test2.txt
tests/test_mutation_waterfall.py