Metadata-Version: 1.1
Name: mutation-waterfall
Version: 0.1.1
Summary: Python library for visualizing mutation landscape as waterfall diagram.
Home-page: https://github.com/dohlee/python-mutation-waterfall
Author: Dohooon Lee
Author-email: apap950419@gmail.com
License: MIT license
Keywords: bioinformatics
Platform: UNKNOWN
Classifier: Development Status :: 5 - Production/Stable
Classifier: Intended Audience :: Developers
Classifier: License :: OSI Approved :: MIT License
Classifier: Operating System :: Unix
Classifier: Operating System :: POSIX
Classifier: Operating System :: Microsoft :: Windows
Classifier: Programming Language :: Python
Classifier: Programming Language :: Python :: 3
Classifier: Programming Language :: Python :: 3.5
Classifier: Programming Language :: Python :: 3.6
Classifier: Topic :: Utilities
